lxd_dyndns/__init__.py
lxd_dyndns/client.py
lxd_dyndns/config.py
lxd_dyndns/dyndns_client.py
lxd_dyndns/run.py
lxd_dyndns-1.1.0.dist-info/METADATA
lxd_dyndns-1.1.0.dist-info/WHEEL
lxd_dyndns-1.1.0.dist-info/entry_points.txt
lxd_dyndns-1.1.0.dist-info/top_level.txt
lxd_dyndns-1.1.0.dist-info/RECORD
