Metadata-Version: 2.1
Name: lxd-dyndns
Version: 1.1.0
Summary: Monitor LXD and perform DNS changes
Author-email: Aisha Tammy <aisha@bsd.ac>
License: ISC
Project-URL: Repository, https://github.com/bsd-ac/lxd-dyndns
Project-URL: License, https://github.com/bsd-ac/lxd-dyndns/blob/main/LICENSE
Keywords: lxd,dyndns
Classifier: Programming Language :: Python
Requires-Python: >=3.11
Requires-Dist: dnspython
Requires-Dist: pylxd
Requires-Dist: uvloop
Requires-Dist: websockets
